[ {
  "id" : 2,
  "pattern" : "grapher",
  "partsOfSpeech" : "NN",
  "index" : {
    "0" : [ "kb=dbp:field Photography", "AllConf=0.5", "triple=e dbp:field Photography", "class=Photographer", "{AllConf=0.5 condAB=1.0 condBA=0.5 supA=5.0 supB=10.0}", "posTag=NN", "interestingness=AllConf", "subject=e", "predicate=http://dbpedia.org/property/field", "object=http://dbpedia.org/resource/Photography" ]
  }
}, {
  "id" : 3,
  "pattern" : "photographer",
  "partsOfSpeech" : "NN",
  "index" : {
    "0" : [ "kb=dbo:nationality United_States", "AllConf=0.454545454545455", "triple=e dbo:nationality United_States", "class=Photographer", "{AllConf=0.454545454545455 condAB=0.833333333333333 condBA=0.454545454545455 supA=6.0 supB=11.0}", "posTag=NN", "interestingness=AllConf", "subject=e", "predicate=http://dbpedia.org/ontology/nationality", "object=http://dbpedia.org/resource/United_States" ],
    "1" : [ "kb=dbp:nationality American@en", "AllConf=0.222222222222222", "triple=e dbp:nationality American@en", "class=Photographer", "{AllConf=0.222222222222222 condAB=0.666666666666667 condBA=0.222222222222222 supA=12.0 supB=36.0}", "posTag=NN", "interestingness=AllConf", "subject=e", "predicate=http://dbpedia.org/property/nationality", "object=\"\"\"American\"\"@en\"" ]
  }
} ]